nyto/__init__.py
nyto/folder.py
nyto/layer.py
nyto/net.py
nyto/net_tool.py
nyto/particle.py
nyto/pool_tool.py
nyto/train_tool.py
nyto/unit_function.py
nyto-0.0.9.dist-info/LICENSE
nyto-0.0.9.dist-info/METADATA
nyto-0.0.9.dist-info/WHEEL
nyto-0.0.9.dist-info/top_level.txt
nyto-0.0.9.dist-info/RECORD
