Metadata-Version: 2.1
Name: nyto
Version: 0.0.9
Summary: Metaheuristic tools for deep learning models
Home-page: UNKNOWN
Author: jimmyzzzz
Author-email: <sciencestudyjimmy@gmsil.com>
License: UNKNOWN
Keywords: python
Platform: UNKNOWN
Classifier: Development Status :: 1 - Planning
Classifier: Intended Audience :: Developers
Classifier: Programming Language :: Python :: 3
Classifier: Operating System :: Unix
Classifier: Operating System :: MacOS :: MacOS X
Classifier: Operating System :: Microsoft :: Windows
Requires-Python: >=3.7
License-File: LICENSE
Requires-Dist: numpy
